large_index/__init__.py
large_index/alias.py
large_index/cluster.py
large_index/config.py
large_index/function.py
large_index/ilm.py
large_index/index.py
large_index/init.py
large_index/log.py
large_index/main.py
large_index/request.py
large_index/structure.py
large_index-0.1.2.dist-info/METADATA
large_index-0.1.2.dist-info/WHEEL
large_index-0.1.2.dist-info/entry_points.txt
large_index-0.1.2.dist-info/top_level.txt
large_index-0.1.2.dist-info/RECORD
