Metadata-Version: 2.1
Name: large-index
Version: 0.1.2
Summary: Rollover big indexes ilm in Elasticsearch
Home-page: https://github.com/antohhh93/large_index
Author: Anton Turko
Author-email: anton_turko@mail.ru
License: MIT
Platform: UNKNOWN
Classifier: Programming Language :: Python :: Implementation
Classifier: Programming Language :: Python :: 3
Classifier: Natural Language :: English
Classifier: License :: OSI Approved :: MIT License
Requires-Dist: requests (>=2)
Requires-Dist: click
